zad/__init__.py
zad/app.py
zad/common.py
zad/models/__init__.py
zad/models/axfr.py
zad/models/main.py
zad/models/nsupdate.py
zad/models/settings.py
zad/pyuic/__init__.py
zad/pyuic/mainwindow.py
zad/pyuic/settings.py
zad/tests/__init__.py
zad/views/__init__.py
zad/views/main.py
zad/views/settings.py
zad/views/tables.py
zad-1.0rc2.dist-info/LICENSE
zad-1.0rc2.dist-info/METADATA
zad-1.0rc2.dist-info/WHEEL
zad-1.0rc2.dist-info/entry_points.txt
zad-1.0rc2.dist-info/top_level.txt
zad-1.0rc2.dist-info/RECORD
